nengo_dl/__init__.py
nengo_dl/benchmarks.py
nengo_dl/builder.py
nengo_dl/config.py
nengo_dl/dists.py
nengo_dl/graph_optimizer.py
nengo_dl/learning_rule_builders.py
nengo_dl/neuron_builders.py
nengo_dl/neurons.py
nengo_dl/objectives.py
nengo_dl/op_builders.py
nengo_dl/process_builders.py
nengo_dl/signals.py
nengo_dl/simulator.py
nengo_dl/tensor_graph.py
nengo_dl/tensor_node.py
nengo_dl/tensorflow_patch.py
nengo_dl/transform_builders.py
nengo_dl/utils.py
nengo_dl/version.py
nengo_dl/tests/__init__.py
nengo_dl/tests/dummies.py
nengo_dl/tests/test_benchmarks.py
nengo_dl/tests/test_builder.py
nengo_dl/tests/test_config.py
nengo_dl/tests/test_dists.py
nengo_dl/tests/test_graph_optimizer.py
nengo_dl/tests/test_learning_rules.py
nengo_dl/tests/test_nengo_tests.py
nengo_dl/tests/test_neurons.py
nengo_dl/tests/test_objectives.py
nengo_dl/tests/test_op_builders.py
nengo_dl/tests/test_processes.py
nengo_dl/tests/test_signals.py
nengo_dl/tests/test_simulator.py
nengo_dl/tests/test_tensor_graph.py
nengo_dl/tests/test_tensor_node.py
nengo_dl/tests/test_tensorflow_patch.py
nengo_dl/tests/test_testing.py
nengo_dl/tests/test_transforms.py
nengo_dl/tests/test_utils.py
nengo_dl/tests/test_version.py
nengo_dl-2.1.0.dist-info/LICENSE.rst
nengo_dl-2.1.0.dist-info/METADATA
nengo_dl-2.1.0.dist-info/WHEEL
nengo_dl-2.1.0.dist-info/entry_points.txt
nengo_dl-2.1.0.dist-info/top_level.txt
nengo_dl-2.1.0.dist-info/RECORD
