Metadata-Version: 2.1
Name: nengo-dl
Version: 2.1.0
Summary: Deep learning integration for Nengo
Home-page: https://www.nengo.ai/nengo-dl
Author: Daniel Rasmussen
Author-email: daniel.rasmussen@appliedbrainresearch.com
License: Free for non-commercial use
Platform: UNKNOWN
Classifier: Development Status :: 5 - Production/Stable
Classifier: Intended Audience :: Science/Research
Classifier: License :: Free for non-commercial use
Classifier: Operating System :: Microsoft :: Windows
Classifier: Operating System :: POSIX :: Linux
Classifier: Programming Language :: Python
Classifier: Programming Language :: Python :: 3.4
Classifier: Programming Language :: Python :: 3.5
Classifier: Programming Language :: Python :: 3.6
Classifier: Topic :: Scientific/Engineering
Classifier: Topic :: Scientific/Engineering :: Artificial Intelligence
Requires-Python: >=3.4
Requires-Dist: nengo (>=2.7.0)
Requires-Dist: numpy (>=1.12.1)
Requires-Dist: tensorflow (>=1.4.0)
Requires-Dist: progressbar2 (>=3.37.1)
Provides-Extra: all
Requires-Dist: jupyter (>=1.0.0) ; extra == 'all'
Requires-Dist: matplotlib (>=2.0.0) ; extra == 'all'
Requires-Dist: nbconvert (!=5.4) ; extra == 'all'
Requires-Dist: nbsphinx (>=0.2.13) ; extra == 'all'
Requires-Dist: nengo-sphinx-theme (>=0.7.0) ; extra == 'all'
Requires-Dist: numpydoc (>=0.6.0) ; extra == 'all'
Requires-Dist: Pillow (>=4.1.1) ; extra == 'all'
Requires-Dist: sphinx (>=1.8.0) ; extra == 'all'
Requires-Dist: sphinx-click (>=1.4.1) ; extra == 'all'
Requires-Dist: click (>=6.7) ; extra == 'all'
Requires-Dist: codespell (>=1.12.0) ; extra == 'all'
Requires-Dist: coverage (>=4.3.4) ; extra == 'all'
Requires-Dist: nbval (>=0.6.0) ; extra == 'all'
Requires-Dist: pylint (>=1.9.2) ; extra == 'all'
Requires-Dist: pytest (>=3.0.4) ; extra == 'all'
Requires-Dist: pytest-xdist (>=1.16.0) ; extra == 'all'
Provides-Extra: docs
Requires-Dist: jupyter (>=1.0.0) ; extra == 'docs'
Requires-Dist: matplotlib (>=2.0.0) ; extra == 'docs'
Requires-Dist: nbconvert (!=5.4) ; extra == 'docs'
Requires-Dist: nbsphinx (>=0.2.13) ; extra == 'docs'
Requires-Dist: nengo-sphinx-theme (>=0.7.0) ; extra == 'docs'
Requires-Dist: numpydoc (>=0.6.0) ; extra == 'docs'
Requires-Dist: Pillow (>=4.1.1) ; extra == 'docs'
Requires-Dist: sphinx (>=1.8.0) ; extra == 'docs'
Requires-Dist: sphinx-click (>=1.4.1) ; extra == 'docs'
Provides-Extra: tests
Requires-Dist: click (>=6.7) ; extra == 'tests'
Requires-Dist: codespell (>=1.12.0) ; extra == 'tests'
Requires-Dist: coverage (>=4.3.4) ; extra == 'tests'
Requires-Dist: matplotlib (>=2.0.0) ; extra == 'tests'
Requires-Dist: nbval (>=0.6.0) ; extra == 'tests'
Requires-Dist: pylint (>=1.9.2) ; extra == 'tests'
Requires-Dist: pytest (>=3.0.4) ; extra == 'tests'
Requires-Dist: pytest-xdist (>=1.16.0) ; extra == 'tests'
